Workbook

Sheet README
A1: Bajaj Motorcycle Knowledge Base
A2: Compiled for a purchase-advisor / TCO system · Accessed 2026-09-05
A4: Purpose | B4: This workbook is a structured knowledge base on Bajaj Auto's current India motorcycle lineup (21 models / ~30 priced variants), covering brand facts, per-model/per-variant identity, pricing, powertrain, dimensions, safety, features, warranty, maintenance, performance/mileage, competitors, customer sentiment, and TCO. It is designed to be queried at VARIANT level, per the brief.
A6: Source tiers used
A7: Tier 1 — OEM official | B7: bajajauto.com product pages, owner's manuals, warranty documents, press releases.
A8: Tier 2 — Regulatory | B8: Government/emission-standard facts (e.g. BS VI) referenced from official manuals.
A9: Tier 3 — Reputable auto publications | B9: BikeWale, ZigWheels, Autocar India, MotorBeam, Team-BHP, 91Wheels, Rushlane, BikeDekho — independent tests, mileage, competitor comparisons.
A10: Tier 4 — Forums / owner sentiment | B10: Owner reviews, forum threads, aggregated sentiment. Never manufacturer fact — opinion/experience only.
A11: Assumption (not sourced) | B11: Values needed for TCO/insurance/financing math that no source publishes. Shown in blue text — edit freely.
A13: Key labeling rule | B13: Every field that Bajaj does not publish is marked "Not published by Bajaj (official site/manuals checked)" — never guessed or backfilled from a competitor's typical spec. Independent (Tier 3/4) figures are ALWAYS kept in separate columns from official (Tier 1) figures, never merged into one number.
A15: Sheet index
B16: • Brand_Manufacturer — Category 1: company, portfolio, philosophy, service, tech, warranty philosophy
B17: • Models_Overview — Category 2: model identity, positioning, target customer, competitors, official links
B18: • Variants — Category 3: every priced SKU with colours, engine config, brakes/ABS, price
B19: • Pricing — Category 4: ex-showroom price detail, source, discrepancy flags (no live on-road/offers — see notes)
B20: • Powertrain — Category 5: full engine specs per model
B21: • Dimensions_Ergonomics — Category 8: L/W/H, wheelbase, seat height, kerb weight (mostly ND — see notes)
B22: • Safety_Chassis — Categories 10-11: brakes, ABS, frame, suspension, tyres
B23: • Technology_Features — Category 12: instrumentation, connectivity, ride modes
B24: • Warranty_Maintenance — Categories 15,17: warranty terms, service intervals, oil grade
B25: • Performance_Mileage — Categories 6-7: OEM claim vs independent test, kept in separate columns
B26: • Competitors — Category 24: direct/segment competitors, tagged Tier 3
B27: • Customer_Reviews — Category 25: aggregated sentiment, tagged Tier 3/4, never presented as fact
... B34: • Sources_Evidence — Category 29: master source log, every fact traceable to a URL + tier
A36: Disclaimer | B36: Prices/specs change; verify current figures on bajajauto.com before any purchase decision. Tier 3/4 data reflects opinions and test conditions of third parties, not Bajaj. TCO/insurance/financing numbers are illustrative assumptions, not quotes.

Sheet Brand_Manufacturer
A1: Brand / Manufacturer Information — Bajaj Auto Ltd
A2: Category 1 · Tier 1 official unless noted
A4: Field | B4: Value | C4: Source
A5: Company name | B5: Bajaj Auto Ltd. | C5: bajajauto.com (site-wide footer)
A6: Parent / group structure | B6: Bajaj Auto Ltd is the flagship, top-level listed company of the Bajaj Group (founded by Jamnalal Bajaj); it owns subsidiaries (Chetak Technology Ltd, Bajaj Auto Credit Ltd, plus units in Indonesia/Netherlands/Thailand/Spain) rather than being owned by a named parent. | C6: bajajauto.com/about-us/about-bajaj-group; bajajauto.com/about-us/bajaj-auto-subsidiaries
A7: Brand positioning / tagline | B7: "The World's Favourite Indian"; "World's most valuable two- and three-wheeler company"; "World No.1 Three-Wheeler" | C7: bajajauto.com; bajajauto.com/about-us/about-bajaj-group
A8: Market positioning by line | B8: Dominar = sports-tourer ("Born To Sprint, Built To Tour"); Pulsar NS/RS = performance-first naked/sport; Avenger = cruiser/lifestyle; Freedom = value/eco commuter (CNG). Platina/CT: Not published by Bajaj (official site/manuals checked) (no explicit tagline found). | C8: bajajauto.com/bikes/dominar/dominar-400; bajajauto.com/bikes/avenger/avenger-street-160; bajajauto.com/bikes/bajaj-freedom/bajaj-freedom-125-ng04
A9: Target customer segments | B9: Pulsar (NS/RS/Classic): performance-oriented street riders. Dominar: touring/adventure-leaning enthusiasts. Avenger: lifestyle/cruiser riders. Freedom 125: cost-conscious, eco-aware daily commuters ("50% fuel-cost savings" messaging). Platina/CT: Not published by Bajaj (official site/manuals checked). | C9: as above
A10: Motorcycle portfolio | B10: Freedom, Pulsar (N / NS / RS / Classic sub-series), Dominar, Avenger, Platina, CT | C10: bajajauto.com/bikes
A11: Scooter portfolio | B11: None currently sold under the Bajaj brand. | C11: bajajauto.com/bikes (no scooter listed)
A12: EV portfolio | B12: Chetak — organized as a SEPARATE brand with its own site (chetak.com), backed by subsidiary Chetak Technology Ltd; not listed inside bajajauto.com/bikes. | C12: chetak.com; bajajauto.com/about-us/bajaj-auto-subsidiaries
A13: Premium / performance portfolio | B13: Dominar (250/400) and Pulsar RS/NS series (esp. NS400Z, RS200, NS200) carry the performance-first framing. | C13: bajajauto.com/bikes
A14: Commuter portfolio | B14: Platina (100/110), CT 110X, and the entry Pulsar 125/N125/NS125 tier. ("Commuter" is an inferred tier label — not an official Bajaj term.) | C14: bajajauto.com/bikes — label inferred, flagged
A15: Touring / adventure portfolio | B15: Dominar 250/400, explicitly marketed as sports-tourers ("Born To Sprint, Built To Tour"). | C15: bajajauto.com/bikes/dominar/dominar-400
... A25: Official manuals | B25: Dedicated download hub with ~30 model/variant owner's manuals as PDFs. | C25: https://www.bajajauto.com/customer-service/owners-manual

Sheet Models_Overview
A1: Product / Model Identity
A2: Category 2 · one row per MODEL (variant detail lives in the Variants sheet)
A4: Brand | B4: Family | C4: Model | D4: Model Year | E4: Category | F4: ICE/EV | G4: Segment | H4: Intended Usage | I4: Positioning | J4: Target Customer | K4: Key Differentiators | L4: Direct Competitors (Tier 3) | M4: Official Product Page | N4: Owner's Manual Hub
A5: Bajaj | B5: Freedom | C5: Bajaj Freedom 125 NG04 | D5: 2026 lineup (as listed, Sept 2026) | E5: Motorcycle | F5: ICE | G5: 125cc CNG bi-fuel commuter | H5: Daily city commute, cost-conscious high-mileage riding | I5: World's first CNG motorcycle; ~50% running-cost saving vs petrol | J5: Cost-conscious, eco-aware daily commuters | K5: Only mass-market CNG motorcycle in India; mono-linked CNG cylinder + 2L petrol reserve | L5: 125cc petrol commuters: TVS Raider 125, Hero Xtreme 125R, Bajaj's own Pulsar NS125 (no direct CNG rival exists) | M5: https://www.bajajauto.com/bikes/bajaj-freedom/bajaj-freedom-125-ng04 | N5: https://www.bajajauto.com/customer-service/owners-manual
A6: Bajaj | B6: Pulsar | C6: Pulsar N125 | D6: 2026 lineup (as listed, Sept 2026) | E6: Motorcycle | F6: ICE | G6: 125cc naked commuter-sport | H6: Urban commute with sporty styling | I6: Entry point to the new-generation Pulsar 'N' naked design language | J6: Young, style-conscious first/second-bike buyers | K6: LED headlamp + Bluetooth console at 125cc price point | L6: TVS Raider 125, Hero Xtreme 125R, Honda Shine/SP125, Hero Glamour/Super Splendor | M6: https://www.bajajauto.com/bikes/pulsar/pulsar-n125 | N6: https://www.bajajauto.com/customer-service/owners-manual
A7: Bajaj | B7: Pulsar | C7: Pulsar N160 | D7: 2026 lineup (as listed, Sept 2026) | E7: Motorcycle | F7: ICE | G7: 160cc naked street | H7: Urban + occasional highway; performance-oriented commuter | I7: Feature-flagship of the N-series naked line | J7: Riders wanting tech (TFT/nav/ride modes) at 160cc | K7: Up to 5 trims spanning 2V/4V engines, mono/dual-channel ABS, TFT w/ Google Maps mirroring on top trim | L7: Honda Unicorn/Hornet lower trims, TVS Apache RTR 160, Yamaha FZ-S FI | M7: https://www.bajajauto.com/bikes/pulsar/pulsar-n160 | N7: https://www.bajajauto.com/customer-service/owners-manual
A8: Bajaj | B8: Pulsar | C8: Pulsar N250 | D8: 2026 lineup (as listed, Sept 2026) | E8: Motorcycle | F8: ICE | G8: 250cc naked street | H8: Urban + confident highway cruising | I8: Quarter-litre naked flagship with USD forks and dual-channel ABS | J8: Upgraders from 150-160cc wanting more performance | K8: SOHC oil-cooled 250, projector headlamp, connected console with ride modes + traction control | L8: Yamaha FZ25, Suzuki Gixxer 250, Bajaj's own Dominar 250 | M8: https://www.bajajauto.com/bikes/pulsar/pulsar-n250 | N8: https://www.bajajauto.com/customer-service/owners-manual
A9: Bajaj | B9: Pulsar | C9: Pulsar NS125 | D9: 2026 lineup (as listed, Sept 2026) | E9: Motorcycle | F9: ICE | G9: 125cc naked street | H9: Urban commute with sportier naked styling than N125 | I9: Naked-street 125 with perimeter frame and 4-valve engine | J9: Style-focused commuters wanting a 'baby NS' | K9: Perimeter frame + 4-valve engine at 125cc; single-channel ABS with 3 ride modes | L9: TVS Raider 125, Hero Xtreme 125R, Bajaj's own N125/Freedom 125 | M9: https://www.bajajauto.com/bikes/pulsar/pulsar-ns125 | N9: https://www.bajajauto.com/customer-service/owners-manual
A10: Bajaj | B10: Pulsar | C10: Pulsar NS160 | D10: 2026 lineup (as listed, Sept 2026) | E10: Motorcycle | F10: ICE | G10: 160cc naked street | H10: Urban + occasional highway | I10: Perimeter-frame naked with twin-spark 4-valve engine | J10: Riders wanting a sportier 160 with dual-channel ABS as standard | K10: Nitrox monoshock w/ canister, dual-channel ABS standard, USD forks | L10: Honda Unicorn/Hornet, TVS Apache RTR 160, Yamaha FZ-S FI | M10: https://www.bajajauto.com/bikes/pulsar/pulsar-ns160 | N10: https://www.bajajauto.com/customer-service/owners-manual
A11: Bajaj | B11: Pulsar | C11: Pulsar NS200 | D11: 2026 lineup (as listed, Sept 2026) | E11: Motorcycle | F11: ICE | G11: 200cc naked street | H11: Urban + confident highway performance riding | I11: Bajaj's benchmark 200cc street-naked performance bike | J11: Performance-focused riders in the 200cc bracket | K11: Liquid-cooled 4V engine, 6-speed, dual-channel ABS, fastest 0-100 in its 3-way comparo group | L11: TVS Apache RTR 200 4V, Honda Hornet 2.0 | M11: https://www.bajajauto.com/bikes/pulsar/pulsar-ns200 | N11: https://www.bajajauto.com/customer-service/owners-manual
A12: Bajaj | B12: Pulsar | C12: Pulsar NS400Z | D12: 2026 lineup (as listed, Sept 2026) | E12: Motorcycle | F12: ICE | G12: 373cc naked street (performance flagship) | H12: Spirited street riding + occasional track/highway | I12: Pulsar range-topper; clutch-less 'Sports Shift' gearing | J12: Enthusiasts moving up from 200-250cc to a genuine performance naked | K12: Sports Shift clutch-less shifting, 320mm front disc w/ sintered pads, 4 ride modes incl. switchable traction control | L12: KTM 390 Duke (primary benchmark); Dominar 400 (sibling, different use-case) | M12: https://www.bajajauto.com/bikes/pulsar/pulsar-ns400z | N12: https://www.bajajauto.com/customer-service/owners-manual
A13: Bajaj | B13: Pulsar | C13: Pulsar RS200 | D13: 2026 lineup (as listed, Sept 2026) | E13: Motorcycle | F13: ICE | G13: 200cc fully-faired sport | H13: Spirited riding + confident highway touring | I13: Bajaj's only fully-faired sport model | J13: Riders wanting race-inspired styling with everyday usability | K13: Full fairing, 6-speed, dual-channel ABS, assist & slipper clutch, projector LED headlamps w/ DRLs | L13: No dedicated 3-way comparo found; cross-shopped with Yamaha R15/FZ25 buyers trading up, and internally with NS200 | M13: https://www.bajajauto.com/bikes/pulsar/pulsar-rs200 | N13: https://www.bajajauto.com/customer-service/owners-manual
A14: Bajaj | B14: Pulsar | C14: Pulsar 125 | D14: 2026 lineup (as listed, Sept 2026) | E14: Motorcycle | F14: ICE | G14: 125cc classic-styled commuter | H14: Daily commute with 'big-bike' classic Pulsar styling | I14: Classic full-headlamp Pulsar design language at 125cc | J14: Buyers wanting Pulsar heritage styling in an affordable displacement | K14: TFT display + premium split seat at 125cc price point | L14: TVS Raider 125, Hero Xtreme 125R, Honda Shine/SP125, Hero Glamour/Super Splendor | M14: https://www.bajajauto.com/bikes/pulsar/pulsar-125 | N14: https://www.bajajauto.com/customer-service/owners-manual
A15: Bajaj | B15: Pulsar | C15: Pulsar 150 | D15: 2026 lineup (as listed, Sept 2026) | E15: Motorcycle | F15: ICE | G15: 150cc classic-styled commuter-sport | H15: Daily commute + weekend spirited riding | I15: Long-running best-seller in Bajaj's classic Pulsar line | J15: Value-conscious riders wanting proven Pulsar heritage | K15: Twin Hydraulic/adjustable Nitrox rear suspension, dual disc + ABS on top trim | L15: Honda Unicorn/SP160, TVS Apache RTR 160, Yamaha FZ-S FI (general 150cc segment) | M15: https://www.bajajauto.com/bikes/pulsar/pulsar-150 | N15: https://www.bajajauto.com/customer-service/owners-manual
... A24: Bajaj | B24: CT | C24: CT 110X | D24: 2026 lineup (as listed, Sept 2026) | E24: Motorcycle | F24: ICE | G24: 110cc rugged/rural commuter | H24: Rough-road commute, small load-carrying, rural/semi-urban use | I24: Bajaj's toughened commuter for rural and rough-road use | J24: Riders needing durability over rough roads and light load-carrying | K24: Circular belly pan, stronger crash guards, third footrest, special carrier, semi-knobby tyres | L24: Hero Splendor Plus, Hero HF Deluxe (incl. Flex Fuel), TVS Sport | M24: https://www.bajajauto.com/bikes/ct/ct-110x | N24: https://www.bajajauto.com/customer-service/owners-manual

Sheet Variants
A1: Variant Information
A2: Category 3 · ~30 priced SKUs across 20 models · Recommendation engine should key off this sheet
A4: Family | B4: Model | C4: Ex-showroom Price (Delhi, INR) | D4: Price Notes / Discrepancy Flags | E4: Colours Available | F4: Engine Config (summary) | G4: Transmission | H4: Front Brake | I4: Rear Brake | J4: ABS Configuration | K4: Warranty | L4: Official Variant/Model URL
A5: Freedom | B5: Bajaj Freedom 125 NG04 | C5: 117499 | D5: 3 priced variants: Disc LED 1,17,499 / Drum LED 1,04,058 / Drum 1,07,159 (ex-showroom Delhi) | E5: Racing Red, Cyber White, Ebony Black, Pewter Grey, Caribbean Blue | F5: 124.6 cc — 9.5 PS (6.99 kW) @ 8,000 rpm, 9.7 Nm @ 5,000 rpm | G5: 5-speed manual, 1-down-4-up [T3] | H5: Disc (Disc LED variant) | I5: Drum or Disc (variant-dependent, size Not published by Bajaj (official site/manuals checked)) | J5: CBS (Combi Braking System) — not full ABS [T3] | K5: 5 yrs / 75,000 km standard policy (company-wide; not individually restated on this model's page) | L5: https://www.bajajauto.com/bikes/bajaj-freedom/bajaj-freedom-125-ng04
A6: Pulsar | B6: Pulsar N125 | C6: 92270 | D6: Page shows 3 close price points (91,692 / 92,270 / 93,158) for BT/non-BT/Disc trims — verify exact trim before quoting | E6: Ebony Black-Cocktail Wine Red, Ebony Black-Purple Fury, Pewter Grey-Citrus Rush | F6: 124.59 cc — 12 PS (8.83 kW) @ 8,500 rpm, 11 Nm @ 6,000 rpm | G6: 5-speed manual | H6: 240 mm disc | I6: 130 mm drum | J6: CBS (Combi Braking System) — not full ABS [T3] | K6: 5 yrs / 75,000 km standard policy | L6: https://www.bajajauto.com/bikes/pulsar/pulsar-n125
A7: Pulsar | B7: Pulsar N160 | C7: 122106 | D7: 5 variants: SD 1,22,106 / TD 1,25,104 / TD Split 1,31,771 / S 1,33,511 / SS 1,42,585 (ex-showroom Delhi) | E7: Black, White, Red, Blue (4 options across variants) | F7: 164.9 cc — 16 PS @ 8,750 rpm (2V) / 18.5 PS @ 9,500 rpm (4V), 14.65 Nm @ 6,750 rpm (2V) / 14.4 Nm @ 8,000 rpm (4V) | G7: 5-speed, 1-down-4-up [T3] | H7: 280 mm disc (SD/S) / 300 mm disc (TD Split/SS) | I7: 130 mm drum (SD) / 230 mm disc (TD/4V) | J7: 1-channel (SD/S) / 2-channel (TD Split/SS) | K7: 5 yrs / 75,000 km (confirmed via this model's own owner's manual) | L7: https://www.bajajauto.com/bikes/pulsar/pulsar-n160
A8: Pulsar | B8: Pulsar N250 | C8: 142202 | D8: Master listing shows 1,42,202; detail page separately showed 1,34,166 — discrepancy, verify current trim/price before quoting | E8: Brooklyn Black, Pearl Metallic White, Glossy Racing Red | F8: 249.07 cc — 24.5 PS (18 kW) @ 8,750 rpm, 21.5 Nm @ 6,500 rpm | G8: 5-speed manual, chain drive [T3] | H8: Disc (Not published by Bajaj (official site/manuals checked) size) | I8: Disc (size not found) [T3] | J8: Dual-channel (standard) | K8: 5 yrs / 75,000 km standard policy | L8: https://www.bajajauto.com/bikes/pulsar/pulsar-n250
A9: Pulsar | B9: Pulsar NS125 | C9: 99622 | D9: 2 variants: LED BT 92,182 / LED BT ABS 99,622 (ex-showroom Delhi) | E9: Fiery Orange, Burnt Red, Beach Blue, Pewter Grey (BT); Black, Pearl White, Blue, Orange, Red (ABS) | F9: 124.45 cc — 12 PS (8.83 kW) @ 8,500 rpm, 11 Nm @ 7,000 rpm | G9: 5-speed manual [T3] | H9: Disc (Not published by Bajaj (official site/manuals checked) size) | I9: Drum (size not found) [T3] | J9: Single-channel ABS with 3 ride modes (ABS variant only) | K9: 5 yrs / 75,000 km standard policy | L9: https://www.bajajauto.com/bikes/pulsar/pulsar-ns125
A10: Pulsar | B10: Pulsar NS160 | C10: 126301 | D10: Page shows two prices (1,20,171 and 1,26,301) without clearly attached variant names — likely SC vs DC USD trims; verify before quoting | E10: Ebony Black, Pearl Metallic White, Cocktail Wine Red, Pewter Grey | F10: 160.3 cc — 17 PS (12.5 kW) @ 9,000 rpm, 14.6 Nm @ 7,250 rpm | G10: 5-speed manual, 1-down-4-up [T3] | H10: Disc (Not published by Bajaj (official site/manuals checked) size) | I10: Disc (Not published by Bajaj (official site/manuals checked) size) | J10: Dual-channel (standard) | K10: 5 yrs / 75,000 km standard policy | L10: https://www.bajajauto.com/bikes/pulsar/pulsar-ns160
A11: Pulsar | B11: Pulsar NS200 | C11: 138302 | D11: Master listing 1,38,302 (SC); page also references 1,32,962 and 1,43,146 for other trims — verify exact trim before quoting | E11: Glossy Ebony Black, Metallic Pearl White, Pewter Grey Blue, Cocktail Wine Red-White | F11: 199.5 cc — 24.5 PS (18 kW) @ 9,750 rpm, 18.74 Nm @ 8,000 rpm | G11: 6-speed manual | H11: Disc (Not published by Bajaj (official site/manuals checked) size) | I11: Disc (Not published by Bajaj (official site/manuals checked) size) | J11: Dual-channel (standard) | K11: 5 yrs / 75,000 km standard policy | L11: https://www.bajajauto.com/bikes/pulsar/pulsar-ns200
A12: Pulsar | B12: Pulsar NS400Z | C12: 186015 | D12: Page shows multiple figures (1,86,015 / 1,92,328 / 1,92,794 / 1,93,830) — likely ex-showroom vs on-road at different times; verify before quoting | E12: Brooklyn Black, Pearl Metallic White, Glossy Racing Red, Pewter Grey | F12: 349.13 cc — 40.6 PS (29.42 kW) @ 9,000 rpm, 33.2 Nm @ 7,500 rpm | G12: Manual with Sports Shift, 6-speed gearbox [T3] | H12: 320 mm disc, sintered pads | I12: 230 mm disc | J12: Dual-channel (standard, across all ride modes) | K12: 5 yrs / 75,000 km standard policy | L12: https://www.bajajauto.com/bikes/pulsar/pulsar-ns400z
A13: Pulsar | B13: Pulsar RS200 | C13: 180528 | D13: Page shows 1,80,528 alongside a separate 'starting price' of 1,71,153 elsewhere — verify before quoting | E13: Brooklyn Black, Pearl Metallic White & Caribbean Blue, Racing Red | F13: 199.5 cc — 24.5 PS (18 kW) @ 9,750 rpm, 18.7 Nm @ 8,000 rpm | G13: 6-speed manual | H13: 300 mm disc | I13: 230 mm disc | J13: Dual-channel (standard) | K13: 5 yrs / 75,000 km standard policy | L13: https://www.bajajauto.com/bikes/pulsar/pulsar-rs200
A14: Pulsar | B14: Pulsar 125 | C14: 104318 | D14: Single trim as listed | E14: Ebony Black+Cyan Blue, Sapphire Blue+Blue Silver, Ebony Black+Magenta Red, Fury Red+Light Orange, Dark Silver+Aqua Blue | F14: 124.38 cc — 11.8 PS (8.68 kW) @ 8,500 rpm, 10.8 Nm @ 6,500 rpm | G14: 5-speed manual [T3] | H14: 260 mm disc [T3] | I14: 130 mm drum [T3] | J14: Not published by Bajaj (official site/manuals checked) | K14: 5 yrs / 75,000 km standard policy | L14: https://www.bajajauto.com/bikes/pulsar/pulsar-125
A15: Pulsar | B15: Pulsar 150 | C15: 111197 | D15: 2 variants referenced: SD 1,11,669 / TD 1,15,481; master listing shows base 1,11,197 — verify exact trim before quoting | E15: Black Gold, Ebony Black Cherry Red, Ebony Black Ink Blue, Ebony Black Dark Grey | F15: 149.5 cc — 14 PS (10.3 kW) @ 8,500 rpm, 13.25 Nm @ 6,500 rpm | G15: 5-speed, 1-down-5-up [T3] | H15: 260 mm disc, 2-piston caliper [T3] | I15: 130 mm drum [T3] (conflicts with 'dual disc' framing on official page — likely variant-dependent) | J15: Single-channel ABS on ABS-equipped variant [T3] | K15: 5 yrs / 75,000 km standard policy | L15: https://www.bajajauto.com/bikes/pulsar/pulsar-150
A16: Pulsar | B16: Pulsar 180 | C16: 122490 | D16: Single trim as listed | E16: Black Gold, Black Blue, Black Grey, Black Red | F16: 178.61 cc — 17 PS (12.5 kW) @ 8,500 rpm, 15 Nm @ 6,500 rpm | G16: 5-speed manual [T3] | H16: 280 mm disc [T3] | I16: 230 mm disc [T3] | J16: Single-channel ABS [T3] | K16: 5 yrs / 75,000 km standard policy | L16: https://www.bajajauto.com/bikes/pulsar/pulsar-180-2026
... A24: CT | B24: CT 110X | C24: 74930 | D24: Ex-showroom 74,930; page separately showed an anomalous 'on-road starting from 67,885' (lower than ex-showroom, implausible) — do not use, verify on live site | E24: Matte Wild Green, Ebony Black-Red, Ebony Black-Blue | F24: 115.45 cc — 9.5 PS (6.99 kW) @ 7,500 rpm, 9.9 Nm @ 5,500 rpm | G24: 4-speed manual [T3] | H24: 130 mm drum [T3] | I24: 110 mm drum [T3] | J24: Not published by Bajaj (official site/manuals checked) | K24: Likely 5 yrs / 75,000 km per company-wide policy (not individually confirmed for this model) | L24: https://www.bajajauto.com/bikes/ct/ct-110x

Sheet Pricing
A1: Pricing
A2: Category 4 · Purchase price only. On-road price = ex-showroom + RTO + insurance + registration + accessories — these vary by state/city and are NOT published centrally by Bajaj, so no single on-road figure is asserted here. Use the TCO_Calculator sheet's assumption-driven on-road estimate instead of treating any number here as final. Promotional offers/discounts are deliberately excluded (no update process for them in this workbook).
A4: Model | B4: Ex-showroom Price (INR) | C4: City/State | D4: Effective / Accessed Date | E4: Price Source | F4: Price Type | G4: Notes
A5: Bajaj Freedom 125 NG04 | B5: 117499 | C5: Delhi | D5: 2026-09-05 | E5: bajajauto.com/bikes (master price listing) | F5: Ex-showroom | G5: 3 priced variants: Disc LED 1,17,499 / Drum LED 1,04,058 / Drum 1,07,159 (ex-showroom Delhi)
A6: Pulsar N125 | B6: 92270 | C6: Delhi | D6: 2026-09-05 | E6: bajajauto.com/bikes (master price listing) | F6: Ex-showroom | G6: Page shows 3 close price points (91,692 / 92,270 / 93,158) for BT/non-BT/Disc trims — verify exact trim before quoting
A7: Pulsar N160 | B7: 122106 | C7: Delhi | D7: 2026-09-05 | E7: bajajauto.com/bikes (master price listing) | F7: Ex-showroom | G7: 5 variants: SD 1,22,106 / TD 1,25,104 / TD Split 1,31,771 / S 1,33,511 / SS 1,42,585 (ex-showroom Delhi)
A8: Pulsar N250 | B8: 142202 | C8: Delhi | D8: 2026-09-05 | E8: bajajauto.com/bikes (master price listing) | F8: Ex-showroom | G8: Master listing shows 1,42,202; detail page separately showed 1,34,166 — discrepancy, verify current trim/price before quoting
A9: Pulsar NS125 | B9: 99622 | C9: Delhi | D9: 2026-09-05 | E9: bajajauto.com/bikes (master price listing) | F9: Ex-showroom | G9: 2 variants: LED BT 92,182 / LED BT ABS 99,622 (ex-showroom Delhi)
A10: Pulsar NS160 | B10: 126301 | C10: Delhi | D10: 2026-09-05 | E10: bajajauto.com/bikes (master price listing) | F10: Ex-showroom | G10: Page shows two prices (1,20,171 and 1,26,301) without clearly attached variant names — likely SC vs DC USD trims; verify before quoting
A11: Pulsar NS200 | B11: 138302 | C11: Delhi | D11: 2026-09-05 | E11: bajajauto.com/bikes (master price listing) | F11: Ex-showroom | G11: Master listing 1,38,302 (SC); page also references 1,32,962 and 1,43,146 for other trims — verify exact trim before quoting
A12: Pulsar NS400Z | B12: 186015 | C12: Delhi | D12: 2026-09-05 | E12: bajajauto.com/bikes (master price listing) | F12: Ex-showroom | G12: Page shows multiple figures (1,86,015 / 1,92,328 / 1,92,794 / 1,93,830) — likely ex-showroom vs on-road at different times; verify before quoting
A13: Pulsar RS200 | B13: 180528 | C13: Delhi | D13: 2026-09-05 | E13: bajajauto.com/bikes (master price listing) | F13: Ex-showroom | G13: Page shows 1,80,528 alongside a separate 'starting price' of 1,71,153 elsewhere — verify before quoting
A14: Pulsar 125 | B14: 104318 | C14: Delhi | D14: 2026-09-05 | E14: bajajauto.com/bikes (master price listing) | F14: Ex-showroom | G14: Single trim as listed
A15: Pulsar 150 | B15: 111197 | C15: Delhi | D15: 2026-09-05 | E15: bajajauto.com/bikes (master price listing) | F15: Ex-showroom | G15: 2 variants referenced: SD 1,11,669 / TD 1,15,481; master listing shows base 1,11,197 — verify exact trim before quoting
A16: Pulsar 180 | B16: 122490 | C16: Delhi | D16: 2026-09-05 | E16: bajajauto.com/bikes (master price listing) | F16: Ex-showroom | G16: Single trim as listed
... A24: CT 110X | B24: 74930 | C24: Delhi | D24: 2026-09-05 | E24: bajajauto.com/bikes (master price listing) | F24: Ex-showroom | G24: Ex-showroom 74,930; page separately showed an anomalous 'on-road starting from 67,885' (lower than ex-showroom, implausible) — do not use, verify on live site

Sheet Powertrain
A1: Engine / Powertrain (ICE) — Bajaj sells no EV motorcycles; see Brand_Manufacturer for the separate Chetak EV brand
A2: Category 5 · Amber [T3] cells (transmission/clutch/starting) are filled from 91Wheels/BikeWale/BikeDekho where bajajauto.com omits them.
A4: Model | B4: Displacement (cc) | C4: Engine Type | D4: Max Power | E4: Max Torque | F4: Transmission | G4: Clutch | H4: Fuel Tank | I4: Starting Mechanism | J4: Emission Standard
A5: Bajaj Freedom 125 NG04 | B5: 124.6 | C5: 4-stroke, air-cooled, bi-fuel (CNG+petrol) | D5: 9.5 PS (6.99 kW) @ 8,000 rpm | E5: 9.7 Nm @ 5,000 rpm | F5: 5-speed manual, 1-down-4-up [T3] | G5: Slipper clutch (91Wheels) / wet multi-plate (BikeWale) — sources disagree [T3] | H5: 2 L petrol reserve + 2 kg / 12.5 L CNG tank | I5: Kick + self-start (91Wheels) / self-start only (BikeWale) — sources disagree [T3] | J5: BS VI (assumed current-lineup compliance; not individually restated on this page)
A6: Pulsar N125 | B6: 124.59 | C6: Air-cooled, single spark, 2-valve | D6: 12 PS (8.83 kW) @ 8,500 rpm | E6: 11 Nm @ 6,000 rpm | F6: 5-speed manual | G6: Wet multi-plate [T3] | H6: 9.5 L | I6: Kick and self-start [T3] | J6: BS VI (assumed)
A7: Pulsar N160 | B7: 164.9 | C7: Oil-cooled, 2V (SD/TD/TD-Split) or 4V (S/SS) | D7: 16 PS @ 8,750 rpm (2V) / 18.5 PS @ 9,500 rpm (4V) | E7: 14.65 Nm @ 6,750 rpm (2V) / 14.4 Nm @ 8,000 rpm (4V) | F7: 5-speed, 1-down-4-up [T3] | G7: Assist & Slipper (all variants) | H7: 14 L | I7: Self-start (kick not confirmed) [T3] | J7: BS VI (confirmed via owner's manual)
A8: Pulsar N250 | B8: 249.07 | C8: Single cylinder, 4-stroke, SOHC, 2-valve, oil-cooled, FI | D8: 24.5 PS (18 kW) @ 8,750 rpm | E8: 21.5 Nm @ 6,500 rpm | F8: 5-speed manual, chain drive [T3] | G8: Assist & slipper | H8: 14 L | I8: Self-start [T3] | J8: BS VI (assumed)
A9: Pulsar NS125 | B9: 124.45 | C9: 4-stroke, SOHC, 4-valve, air-cooled, BS VI | D9: 12 PS (8.83 kW) @ 8,500 rpm | E9: 11 Nm @ 7,000 rpm | F9: 5-speed manual [T3] | G9: Slipper (91Wheels) / wet multi-plate (BikeWale) — sources disagree [T3] | H9: 12 L | I9: Kick and self-start [T3] | J9: BS VI (stated on page)
A10: Pulsar NS160 | B10: 160.3 | C10: Oil-cooled, twin spark, 4-valve FI | D10: 17 PS (12.5 kW) @ 9,000 rpm | E10: 14.6 Nm @ 7,250 rpm | F10: 5-speed manual, 1-down-4-up [T3] | G10: Wet multi-plate [T3] | H10: 12 L | I10: Kick and self-start [T3] | J10: BS VI (assumed)
A11: Pulsar NS200 | B11: 199.5 | C11: Liquid-cooled, 4-valve FI | D11: 24.5 PS (18 kW) @ 9,750 rpm | E11: 18.74 Nm @ 8,000 rpm | F11: 6-speed manual | G11: Slipper clutch [T3] | H11: 12 L | I11: Self-start [T3] | J11: BS VI (assumed)
A12: Pulsar NS400Z | B12: 349.13 | C12: Liquid-cooled | D12: 40.6 PS (29.42 kW) @ 9,000 rpm | E12: 33.2 Nm @ 7,500 rpm | F12: Manual with Sports Shift, 6-speed gearbox [T3] | G12: Slipper clutch [T3] | H12: 12 L | I12: Self-start [T3] | J12: BS VI (assumed)
A13: Pulsar RS200 | B13: 199.5 | C13: Liquid-cooled, single-spark 4-valve FI | D13: 24.5 PS (18 kW) @ 9,750 rpm | E13: 18.7 Nm @ 8,000 rpm | F13: 6-speed manual | G13: Assist & slipper | H13: 13 L | I13: Self-start [T3] | J13: BS VI (stated: '200cc BSVI, FI Engine')
A14: Pulsar 125 | B14: 124.38 | C14: Not published by Bajaj (official site/manuals checked) | D14: 11.8 PS (8.68 kW) @ 8,500 rpm | E14: 10.8 Nm @ 6,500 rpm | F14: 5-speed manual [T3] | G14: Wet multi-plate [T3] | H14: 15 L | I14: Kick and self-start [T3] | J14: BS VI (assumed)
A15: Pulsar 150 | B15: 149.5 | C15: 4-stroke, 2-valve, twin spark, BS VI FI | D15: 14 PS (10.3 kW) @ 8,500 rpm | E15: 13.25 Nm @ 6,500 rpm | F15: 5-speed, 1-down-5-up [T3] | G15: Wet multi-plate [T3] | H15: 15 L | I15: Kick and self-start [T3] | J15: BS VI (explicitly stated on page)
A16: Pulsar 180 | B16: 178.61 | C16: Not published by Bajaj (official site/manuals checked) | D16: 17 PS (12.5 kW) @ 8,500 rpm | E16: 15 Nm @ 6,500 rpm | F16: 5-speed manual [T3] | G16: Wet multi-plate [T3] | H16: 15 L | I16: Self-start only [T3] | J16: BS VI (assumed)
... A24: CT 110X | B24: 115.45 | C24: 4-stroke, single cylinder, DTS-i | D24: 9.5 PS (6.99 kW) @ 7,500 rpm | E24: 9.9 Nm @ 5,500 rpm | F24: 4-speed manual [T3] | G24: Wet multi-plate [T3] | H24: 11 L | I24: Electric start | J24: BS VI (assumed)

Sheet Dimensions_Ergonomics
A1: Dimensions & Ergonomics
A2: Category 8 · Bajaj's own marketing pages omit almost all L/W/H/seat-height/kerb-weight figures. Amber cells marked [T3] are filled from 91Wheels/BikeWale/BikeDekho spec-aggregator pages (Tier 3, re-publishing manufacturer spec sheets) — genuinely absent fields (red italic) remain unfilled rather than guessed.
A4: Model | B4: Length (mm) | C4: Width (mm) | D4: Height (mm) | E4: Wheelbase (mm) | F4: Ground Clearance (mm) | G4: Seat Height (mm) | H4: Kerb Weight (kg) | I4: Fuel Tank (L)
A5: Bajaj Freedom 125 NG04 | B5: Not published by Bajaj (official site/manuals checked) | C5: Not published by Bajaj (official site/manuals checked) | D5: Not published by Bajaj (official site/manuals checked) | E5: 1,340 mm [T3] | F5: 170 mm [T3] | G5: 825 mm [T3] | H5: ~148 kg (147.8-149 kg across sources) [T3] | I5: 2 L petrol reserve + 2 kg / 12.5 L CNG tank
A6: Pulsar N125 | B6: Not published by Bajaj (official site/manuals checked) | C6: Not published by Bajaj (official site/manuals checked) | D6: Not published by Bajaj (official site/manuals checked) | E6: 1,295 mm | F6: 198 mm | G6: 795 mm [T3] | H6: 125 kg | I6: 9.5 L
A7: Pulsar N160 | B7: 1,989 mm [T3] | C7: 743 mm [T3] | D7: 1,050 mm [T3] | E7: 1,358 mm | F7: 165 mm [T3] | G7: 795 mm | H7: 154 kg [T3] | I7: 14 L
A8: Pulsar N250 | B8: 1,989 mm [T3] | C8: 743 mm [T3] | D8: 1,050 mm [T3] | E8: 1,342-1,351 mm (sources vary) [T3] | F8: 165 mm [T3] | G8: 795-800 mm (sources vary) [T3] | H8: 162-164 kg (sources vary) [T3] | I8: 14 L
A9: Pulsar NS125 | B9: 2,018 mm [T3] | C9: 810 mm [T3] | D9: 1,078 mm [T3] | E9: 1,353-1,370 mm (sources vary) [T3] | F9: 178-179 mm [T3] | G9: 805 mm [T3] | H9: 144-146 kg [T3] | I9: 12 L
A10: Pulsar NS160 | B10: 2,017 mm [T3] | C10: 804 mm [T3] | D10: 1,060 mm [T3] | E10: 1,372 mm [T3] | F10: 170-176 mm [T3] | G10: 805 mm [T3] | H10: 152 kg [T3] | I10: 12 L
A11: Pulsar NS200 | B11: 2,017 mm [T3] | C11: 804 mm [T3] | D11: 1,075 mm [T3] | E11: 1,363 mm [T3] | F11: 168 mm [T3] | G11: 805 mm [T3] | H11: 158 kg [T3] | I11: 12 L
A12: Pulsar NS400Z | B12: 1,990 mm [T3] | C12: 846 mm [T3] | D12: 1,057 mm [T3] | E12: 1,346 mm [T3] | F12: 168 mm [T3] | G12: 805 mm [T3] | H12: 176 kg [T3] | I12: 12 L
A13: Pulsar RS200 | B13: 1,999 mm [T3] | C13: 765 mm [T3] | D13: 1,114 mm [T3] | E13: 1,345 mm [T3] | F13: 157 mm [T3] | G13: 810 mm [T3] | H13: 166 kg [T3] | I13: 13 L
A14: Pulsar 125 | B14: 2,055 mm [T3] | C14: 755 mm [T3] | D14: 1,060 mm [T3] | E14: 1,320 mm [T3] | F14: 184 mm [T3] | G14: 795 mm [T3] | H14: 131 kg [T3] (Bajaj's own page meta description separately stated 150 kg — discrepancy, verify) | I14: 15 L
A15: Pulsar 150 | B15: 2,055 mm [T3] | C15: 765 mm [T3] | D15: 1,060 mm [T3] | E15: 1,320 mm | F15: 165 mm [T3] | G15: 785 mm [T3] | H15: 148-150 kg [T3] (matches page meta description of 150 kg) | I15: 15 L
... A24: CT 110X | B24: 1,998 mm [T3] | C24: 788 mm [T3] | D24: 1,098 mm [T3] | E24: 1,285 mm [T3] | F24: 170 mm [T3] | G24: 810 mm [T3] | H24: 124 kg [T3] | I24: 11 L

Sheet Safety_Chassis
A1: Safety & Chassis / Suspension / Handling
A2: Categories 10-11 · Objective specs only — no 'safest bike' claims. Compare ABS configuration and brake sizing directly per the brief's guidance. Amber [T3] cells are filled from 91Wheels/BikeWale/BikeDekho where bajajauto.com doesn't publish the figure.
A4: Model | B4: Front Brake | C4: Rear Brake | D4: ABS Configuration | E4: Frame/Chassis | F4: Front Suspension | G4: Rear Suspension | H4: Front Tyre | I4: Rear Tyre | J4: Wheel Type/Size
A5: Bajaj Freedom 125 NG04 | B5: Disc (Disc LED variant) | C5: Drum or Disc (variant-dependent, size Not published by Bajaj (official site/manuals checked)) | D5: CBS (Combi Braking System) — not full ABS [T3] | E5: Protective Trellis Frame | F5: Telescopic fork (travel not found) [T3] | G5: Mono-linked type, double-rate spring (travel Not published by Bajaj (official site/manuals checked)) | H5: 17 in wheel; exact tyre size not found [T3] | I5: 120/70-16 | J5: Alloy; front 17", rear 16" [T3]
A6: Pulsar N125 | B6: 240 mm disc | C6: 130 mm drum | D6: CBS (Combi Braking System) — not full ABS [T3] | E6: Perimeter frame (91Wheels) / diamond frame (BikeWale) — sources disagree [T3] | F6: Telescopic, 125 mm travel | G6: Monoshock, 125 mm travel | H6: 80/100-17 | I6: 110/80-17 (tubeless) | J6: Alloy, 17 in front & rear, tubeless tyres [T3]
A7: Pulsar N160 | B7: 280 mm disc (SD/S) / 300 mm disc (TD Split/SS) | C7: 130 mm drum (SD) / 230 mm disc (TD/4V) | D7: 1-channel (SD/S) / 2-channel (TD Split/SS) | E7: Tubular frame [T3] | F7: 33 mm USD (2V) / 37 mm USD (4V S/SS) | G7: Monoshock, 120 mm stroke (SD/TD) / 130 mm stroke (TD Split/S/SS) | H7: 110/70-17 | I7: 130/70-17 (radial on SS) | J7: Alloy, 17 in [T3]
A8: Pulsar N250 | B8: Disc (Not published by Bajaj (official site/manuals checked) size) | C8: Disc (size not found) [T3] | D8: Dual-channel (standard) | E8: Tubular frame [T3] | F8: Golden USD forks (travel Not published by Bajaj (official site/manuals checked)) | G8: Nitrox Monoshock (travel Not published by Bajaj (official site/manuals checked)) | H8: 110/70-R17 [T3] | I8: 140/70-R17 [T3] | J8: Alloy, 17 in [T3]
A9: Pulsar NS125 | B9: Disc (Not published by Bajaj (official site/manuals checked) size) | C9: Drum (size not found) [T3] | D9: Single-channel ABS with 3 ride modes (ABS variant only) | E9: Perimeter frame | F9: Telescopic (travel not found) [T3] | G9: Monoshock (type/travel Not published by Bajaj (official site/manuals checked)) | H9: 17 in wheel; exact tyre spec not found [T3] | I9: 17 in wheel; exact tyre spec not found [T3] | J9: Alloy, 17 in front & rear [T3]
A10: Pulsar NS160 | B10: Disc (Not published by Bajaj (official site/manuals checked) size) | C10: Disc (Not published by Bajaj (official site/manuals checked) size) | D10: Dual-channel (standard) | E10: Perimeter frame | F10: USD forks (travel Not published by Bajaj (official site/manuals checked)) | G10: Nitrox monoshock w/ canister (travel Not published by Bajaj (official site/manuals checked)) | H10: 17 in wheel; exact tyre spec not found [T3] | I10: 17 in wheel; exact tyre spec not found [T3] | J10: Alloy, 17 in front & rear [T3]
A11: Pulsar NS200 | B11: Disc (Not published by Bajaj (official site/manuals checked) size) | C11: Disc (Not published by Bajaj (official site/manuals checked) size) | D11: Dual-channel (standard) | E11: Perimeter frame | F11: USD forks (travel Not published by Bajaj (official site/manuals checked)) | G11: Nitrox monoshock w/ canister (travel not found) [T3] | H11: R17 (exact tyre spec not found) [T3] | I11: Not published by Bajaj (official site/manuals checked) | J11: R17 wheel; alloy/spoke designation not found [T3]
A12: Pulsar NS400Z | B12: 320 mm disc, sintered pads | C12: 230 mm disc | D12: Dual-channel (standard, across all ride modes) | E12: Hydroformed tubular ('street-fighter' perimeter-style) frame [T3] | F12: 43 mm USD forks (travel Not published by Bajaj (official site/manuals checked)) | G12: Monoshock with Nitrox, 6-step adjustable preload (travel not found) [T3] | H12: Radial | I12: Radial, 150-section | J12: Not published by Bajaj (official site/manuals checked)
A13: Pulsar RS200 | B13: 300 mm disc | C13: 230 mm disc | D13: Dual-channel (standard) | E13: Perimeter frame | F13: Telescopic w/ anti-friction bush (travel Not published by Bajaj (official site/manuals checked)) | G13: Nitrox monoshock w/ canister (travel Not published by Bajaj (official site/manuals checked)) | H13: 110/70-17 | I13: 140/70-17 | J13: 17 in
A14: Pulsar 125 | B14: 260 mm disc [T3] | C14: 130 mm drum [T3] | D14: Not published by Bajaj (official site/manuals checked) | E14: Double-cradle frame [T3] | F14: Telescopic, 31 mm, 125 mm travel [T3] | G14: Monoshock, 110 mm travel [T3] | H14: 80/100-17 [T3] | I14: 100/90-17 [T3] | J14: Alloy, ~17 in [T3]
A15: Pulsar 150 | B15: 260 mm disc, 2-piston caliper [T3] | C15: 130 mm drum [T3] (conflicts with 'dual disc' framing on official page — likely variant-dependent) | D15: Single-channel ABS on ABS-equipped variant [T3] | E15: Double cradle frame [T3] | F15: Telescopic, 33 mm, 125 mm travel [T3] | G15: Twin Hydraulic / adjustable Nitrox rear suspension, ~110 mm travel [T3] | H15: 80/100-17 [T3] | I15: 100/90-17 [T3] | J15: Alloy, 17 in [T3]
... A24: CT 110X | B24: 130 mm drum [T3] | C24: 110 mm drum [T3] | D24: Not published by Bajaj (official site/manuals checked) | E24: Square-tube, single down-tube with lower cradle [T3] | F24: Hydraulic telescopic, 125 mm travel [T3] | G24: Spring-in-Spring (SNS), 100 mm wheel travel | H24: Semi-knobby, 2.75-17 [T3] | I24: Semi-knobby, 3.00-17 [T3] | J24: Alloy, 17 in [T3]

Sheet Technology_Features
A1: Technology & Features
A2: Category 12 · Instrumentation, Bluetooth/connectivity, ride modes, convenience features
A4: Model | B4: Instrument Cluster | C4: Connectivity / Smart Features
A5: Bajaj Freedom 125 NG04 | B5: Fully digital speedometer | C5: Bluetooth — call alerts w/ caller ID, missed-call indication, battery life
A6: Pulsar N125 | B6: Digital console (Bluetooth on select variant) | C6: Call accept/reject, missed-call/message alerts, fuel/economy readouts; USB charging
A7: Pulsar N160 | B7: Monochrome LCD (SD/TD) / 5in colour LCD (S) / 5in TFT (SS) | C7: Bluetooth all; WiFi + Google Maps mirroring, turn-by-turn nav on SS
A8: Pulsar N250 | B8: Connected digital console | C8: Bluetooth, navigation, ride modes, traction control
A9: Pulsar NS125 | B9: Bluetooth-enabled digital console | C9: Navigation & smart connectivity
A10: Pulsar NS160 | B10: Bluetooth-connected digital console | C10: Navigation, ABS ride modes, USB charging, all-LED lighting
A11: Pulsar NS200 | B11: Bluetooth-connected digital console | C11: Gear-position indicator, distance-to-empty, turn-by-turn nav, ABS ride modes
A12: Pulsar NS400Z | B12: Bluetooth-enabled connected console, bonded-glass LCD | C12: Calls, music, lap timing, navigation
A13: Pulsar RS200 | B13: Digital console w/ Bluetooth, bonded-glass LCD | C13: ABS ride modes (Road/Rain/Off-road)
A14: Pulsar 125 | B14: TFT display | C14: Bluetooth connectivity, turn-by-turn navigation, USB Type-C charging (optional), low-battery alert via app [T3]
A15: Pulsar 150 | B15: Digital console w/ Bluetooth (select variant); analogue on base SD | C15: USB charging, all-LED lighting
... A24: CT 110X | B24: Analogue [T3] | C24: USB charging port — no Bluetooth/navigation found [T3]

Sheet Warranty_Maintenance
A1: Warranty & Maintenance
A2: Categories 15 & 17 · Confirmed directly on Pulsar N160 & Dominar 250 owner's manuals; applied as company-wide policy elsewhere and flagged where not individually verified.
A4: Model | B4: Warranty | C4: First Service | D4: Periodic Service Interval | E4: Engine Oil Grade | F4: Source
A5: Bajaj Freedom 125 NG04 | B5: 5 yrs / 75,000 km standard policy (company-wide; not individually restated on this model's page) | C5: 500-750 km (free) | D5: 10,000 km oil change / 5,000 km check | E5: Bajaj 10000-series oil (grade varies by model; not individually confirmed) | F5: Applied from Pulsar N160 / Dominar 250 manuals — not individually confirmed for this model
A6: Pulsar N125 | B6: 5 yrs / 75,000 km standard policy | C6: 500-750 km (free) | D6: 10,000 km oil change / 5,000 km check | E6: Bajaj 10000-series oil (grade varies by model; not individually confirmed) | F6: Applied from Pulsar N160 / Dominar 250 manuals — not individually confirmed for this model
A7: Pulsar N160 | B7: 5 yrs / 75,000 km (confirmed via this model's own owner's manual) | C7: 500-750 km (free) | D7: 10,000 km oil change / 5,000 km check | E7: Bajaj 10000 SAE 20W50, JASO MA2, API SN | F7: Owner's manual (this model)
A8: Pulsar N250 | B8: 5 yrs / 75,000 km standard policy | C8: 500-750 km (free) | D8: 10,000 km oil change / 5,000 km check | E8: Bajaj 10000-series oil (grade varies by model; not individually confirmed) | F8: Applied from Pulsar N160 / Dominar 250 manuals — not individually confirmed for this model
A9: Pulsar NS125 | B9: 5 yrs / 75,000 km standard policy | C9: 500-750 km (free) | D9: 10,000 km oil change / 5,000 km check | E9: Bajaj 10000-series oil (grade varies by model; not individually confirmed) | F9: Applied from Pulsar N160 / Dominar 250 manuals — not individually confirmed for this model
A10: Pulsar NS160 | B10: 5 yrs / 75,000 km standard policy | C10: 500-750 km (free) | D10: 10,000 km oil change / 5,000 km check | E10: Bajaj 10000-series oil (grade varies by model; not individually confirmed) | F10: Applied from Pulsar N160 / Dominar 250 manuals — not individually confirmed for this model
A11: Pulsar NS200 | B11: 5 yrs / 75,000 km standard policy | C11: 500-750 km (free) | D11: 10,000 km oil change / 5,000 km check | E11: Bajaj 10000-series oil (grade varies by model; not individually confirmed) | F11: Applied from Pulsar N160 / Dominar 250 manuals — not individually confirmed for this model
A12: Pulsar NS400Z | B12: 5 yrs / 75,000 km standard policy | C12: 500-750 km (free) | D12: 10,000 km oil change / 5,000 km check | E12: Bajaj 10000-series oil (grade varies by model; not individually confirmed) | F12: Applied from Pulsar N160 / Dominar 250 manuals — not individually confirmed for this model
A13: Pulsar RS200 | B13: 5 yrs / 75,000 km standard policy | C13: 500-750 km (free) | D13: 10,000 km oil change / 5,000 km check | E13: Bajaj 10000-series oil (grade varies by model; not individually confirmed) | F13: Applied from Pulsar N160 / Dominar 250 manuals — not individually confirmed for this model
A14: Pulsar 125 | B14: 5 yrs / 75,000 km standard policy | C14: 500-750 km (free) | D14: 10,000 km oil change / 5,000 km check | E14: Bajaj 10000-series oil (grade varies by model; not individually confirmed) | F14: Applied from Pulsar N160 / Dominar 250 manuals — not individually confirmed for this model
A15: Pulsar 150 | B15: 5 yrs / 75,000 km standard policy | C15: 500-750 km (free) | D15: 10,000 km oil change / 5,000 km check | E15: Bajaj 10000-series oil (grade varies by model; not individually confirmed) | F15: Applied from Pulsar N160 / Dominar 250 manuals — not individually confirmed for this model
... A24: CT 110X | B24: Likely 5 yrs / 75,000 km per company-wide policy (not individually confirmed for this model) | C24: 500-750 km (free) | D24: 10,000 km oil change / 5,000 km check | E24: Bajaj 10000-series oil (grade varies by model; not individually confirmed) | F24: Applied from Pulsar N160 / Dominar 250 manuals — not individually confirmed for this model

Sheet Performance_Mileage
A1: Performance & Mileage — Manufacturer Claim vs Independent Test (never merged)
A2: Categories 6-7 · Bajaj's own pages rarely state 0-60/0-100/top-speed or ARAI mileage; where a claim column is empty, Bajaj has not published one.
A4: Model | B4: OEM Claimed Mileage (Tier 1/ARAI) | C4: Independent Mileage (Tier 3) | D4: Mileage Source | E4: OEM Claimed Performance | F4: Independent Performance (Tier 3) | G4: Performance Source
A5: Bajaj Freedom 125 NG04 | B5: CNG ~100 km/kg (site claim); petrol reserve range ~130 km | C5: 104 km/kg city (relaxed) / 80 km/kg highway (BikeWale test); 85 km/kg over 140km mixed (ZigWheels) | D5: BikeWale, ZigWheels (Tier 3) | E5: Not published by Bajaj on model pages | F5: Not published by Bajaj (official site/manuals checked)
A6: Pulsar N125 | B6: 60 km/l (ARAI, as republished by 91Wheels/BikeWale) [T3] | C6: Not found on Tier-3 sites checked (91Wheels/BikeWale/BikeDekho/ZigWheels) as a distinct figure from N160 | E6: Not published by Bajaj on model pages | F6: Not published by Bajaj (official site/manuals checked)
A7: Pulsar N160 | B7: 51.6 km/l (ARAI, per Tier-3 citation) | C7: 47 km/l owner-reported (range 46-55) | D7: BikeWale (Tier 3) | E7: Not published by Bajaj on model pages | F7: Not published by Bajaj (official site/manuals checked)
A8: Pulsar N250 | B8: 44 km/l (ARAI, per Tier-3 citation) | C8: 40 km/l aggregate (BikeWale); 30-37 km/l avg, peak 49 km/l over 3,395 km long-term test (MotorBeam) | D8: BikeWale, MotorBeam (Tier 3) | E8: Not published by Bajaj on model pages | F8: Not published by Bajaj (official site/manuals checked)
A9: Pulsar NS125 | B9: 46.9 km/l (ARAI, per Tier-3 citation) | C9: Site (91Wheels) flags 'insufficient data' — no reliable figure | D9: 91Wheels (Tier 3) | E9: Not published by Bajaj on model pages | F9: Not published by Bajaj (official site/manuals checked)
A10: Pulsar NS160 | B10: 52.2 km/l (ARAI, per Tier-3 citation) | C10: 44 km/l owner-reported | D10: BikeWale (Tier 3) | E10: Not published by Bajaj on model pages | F10: Not published by Bajaj (official site/manuals checked)
A11: Pulsar NS200 | B11: 36 km/l (ARAI, per Tier-3 citation) | C11: Site (91Wheels) flags 'insufficient data' despite the model's popularity | D11: 91Wheels (Tier 3) | E11: Not published by Bajaj on model pages | F11: 0-60 km/h 4.21 s; 0-100 km/h 11.68 s (quickest of a 3-bike comparison test) | G11: ZigWheels 3-way comparo w/ Apache RTR 200 4V & Hornet 2.0 (Tier 3)
A12: Pulsar NS400Z | B12: Up to 28.5 km/l (ARAI, as republished by 91Wheels) [T3] | C12: 27.52 km/l city / 29.62 km/l highway ('not particularly impressive for this engine size' per reviewer) | D12: Autocar India road test (Tier 3) | E12: Not published by Bajaj on model pages | F12: 0-100 km/h 'just under 7 seconds' in wet conditions; top speed not independently confirmed | G12: Autocar India (Tier 3)
A13: Pulsar RS200 | B13: Up to 35 km/l (ARAI, as republished by 91Wheels) [T3] | C13: 36.5 km/l during a MotorBeam test ride | D13: MotorBeam (Tier 3) | E13: Not published by Bajaj on model pages | F13: 0-60 km/h 3.92 s; 0-100 km/h 10.12 s; top speed 141 km/h on VBOX (console over-read 152 km/h) | G13: MotorBeam test-ride review (Tier 3)
A14: Pulsar 125 | B14: ARAI range ~50-55 km/l per BikeDekho [T3] | C14: ~30-60 km/l range cited; ~50 km/l 'optimistic middle' | D14: BikeWale (Tier 3) | E14: Not published by Bajaj on model pages | F14: Not published by Bajaj (official site/manuals checked)
A15: Pulsar 150 | B15: 47.5 km/l (ARAI, per BikeDekho) [T3] | C15: 45-52 km/l city, 50-65 km/l highway (owner range 33-60 km/l) | D15: BikeWale (Tier 3) | E15: Not published by Bajaj on model pages | F15: Not published by Bajaj (official site/manuals checked)
A16: Pulsar 180 | B16: Not published by Bajaj (official site/manuals checked) | C16: Too newly relaunched (2026) — no independent data found yet | E16: Not published by Bajaj on model pages | F16: Not published by Bajaj (official site/manuals checked)
A17: Pulsar 220F | B17: Not published by Bajaj (official site/manuals checked) | C17: 43 km/l owner-reported (one owner: 45 km/l after 15,000+ km) | D17: BikeWale (Tier 3) | E17: Not published by Bajaj on model pages | F17: Not published by Bajaj (official site/manuals checked)
A18: Dominar 250 | B18: 32 km/l (ARAI, explicitly labeled by 91Wheels; BikeDekho separately shows an unlabeled ~35 km/l figure) [T3] | C18: 32 km/l owner-reported | D18: BikeWale (Tier 3) | E18: Not published by Bajaj on model pages | F18: Not published by Bajaj (official site/manuals checked)
A19: Dominar 400 | B19: 30 km/l (ARAI, explicitly labeled by 91Wheels) [T3] | C19: 30 kmpl owner-reported (range 25-30); one 10,000km owner cites ~22-24 kmpl | D19: BikeWale, Team-BHP (Tier 3) | E19: Not published by Bajaj on model pages | F19: 0-100 km/h ~8.5 s independent estimate (vs 8.23s claimed); top speed ~145 km/h tested (vs 148 km/h claimed); speedo over-reads to 165-170 | G19: CarBlogIndia (Tier 3, lower-confidence — not a flagship publication)
A20: Avenger 220 Cruise | B20: 40 km/l (ARAI) [T3] | C20: 39 kmpl owner-average (range 28-50) | D20: BikeWale (Tier 3) | E20: Not published by Bajaj on model pages | F20: Not published by Bajaj (official site/manuals checked)
A21: Avenger 220 Street | B21: 40 km/l (ARAI) [T3] | C21: No distinct figure found separate from the Cruise variant | E21: Not published by Bajaj on model pages | F21: Not published by Bajaj (official site/manuals checked)
A22: Platina 100 | B22: 70 km/l (ARAI, per BikeDekho) [T3] | C22: 65-88 kmpl typical; one owner as low as 56 kmpl vs an expected ~85 kmpl | D22: BikeWale reviews (Tier 3) | E22: Not published by Bajaj on model pages | F22: Not published by Bajaj (official site/manuals checked)
A23: Platina 110 Drum | B23: 70 km/l (ARAI) [T3] | C23: 70 kmpl owner-reported average (range ~50-70) | D23: 91Wheels (Tier 3) | E23: Not published by Bajaj on model pages | F23: Not published by Bajaj (official site/manuals checked)
A24: CT 110X | B24: 70 kmpl (ARAI, per Tier-3 citation) | C24: ~75 kmpl in a '100ml fuel' video test | D24: IndianAutosBlog, ZigWheels (Tier 3) | E24: Not published by Bajaj on model pages | F24: Not published by Bajaj (official site/manuals checked)

Sheet Competitors
A1: Competitor Information
A2: Category 24 · Identified from reputable auto-publication comparisons — not exhaustive, and never framed as 'only consider Bajaj'. Use alongside Performance_Mileage and Variants to build cross-brand shortlists.
A4: Model | B4: Direct/Segment Competitors | C4: Source (Tier 3)
A5: Bajaj Freedom 125 NG04 | B5: 125cc petrol commuters: TVS Raider 125, Hero Xtreme 125R, Bajaj's own Pulsar NS125 (no direct CNG rival exists) | C5: Rushlane, ZigWheels (Tier 3)
A6: Pulsar N125 | B6: TVS Raider 125, Hero Xtreme 125R, Honda Shine/SP125, Hero Glamour/Super Splendor | C6: Rushlane (Tier 3)
A7: Pulsar N160 | B7: Honda Unicorn/Hornet lower trims, TVS Apache RTR 160, Yamaha FZ-S FI | C7: General segment framing, BikeWale/ZigWheels (Tier 3)
A8: Pulsar N250 | B8: Yamaha FZ25, Suzuki Gixxer 250, Bajaj's own Dominar 250 | C8: ZigWheels 4-way comparo (Tier 3)
A9: Pulsar NS125 | B9: TVS Raider 125, Hero Xtreme 125R, Bajaj's own N125/Freedom 125 | C9: Rushlane (Tier 3)
A10: Pulsar NS160 | B10: Honda Unicorn/Hornet, TVS Apache RTR 160, Yamaha FZ-S FI | C10: General segment framing (Tier 3)
A11: Pulsar NS200 | B11: TVS Apache RTR 200 4V, Honda Hornet 2.0 | C11: Autocar India, ZigWheels, MotorBeam (Tier 3)
A12: Pulsar NS400Z | B12: KTM 390 Duke (primary benchmark); Dominar 400 (sibling, different use-case) | C12: BikeWale, Autocar India (Tier 3)
A13: Pulsar RS200 | B13: No dedicated 3-way comparo found; cross-shopped with Yamaha R15/FZ25 buyers trading up, and internally with NS200 | C13: Editorial framing (Tier 3, low confidence)
A14: Pulsar 125 | B14: TVS Raider 125, Hero Xtreme 125R, Honda Shine/SP125, Hero Glamour/Super Splendor | C14: Rushlane (Tier 3)
A15: Pulsar 150 | B15: Honda Unicorn/SP160, TVS Apache RTR 160, Yamaha FZ-S FI (general 150cc segment) | C15: General segment framing (Tier 3)
... A24: CT 110X | B24: Hero Splendor Plus, Hero HF Deluxe (incl. Flex Fuel), TVS Sport | C24: BikeDekho (Tier 3)

Sheet Customer_Reviews
A1: Customer Reviews / Real-World Experience
A2: Category 25 · AGGREGATED SENTIMENT, not verified fact — never present as objective truth. Distinguished explicitly from official Bajaj facts elsewhere in this workbook.
A4: Model Family | B4: Common Praise (aggregated sentiment) | C4: Common Complaints (aggregated sentiment) | D4: Source(s) | E4: Tier
A5: Pulsar (125-400cc range) | B5: Engine refinement/exhaust note often called best-in-class within Bajaj's range (esp. N250); strong low-end acceleration and city agility; long-term engine durability reported by very high-mileage owners (100,000+ km cases). | C5: Recurring electrical/CDI and speedometer faults on older-generation models; carb/FI driveability issues (rough idle, hesitation) tied to fuel quality; noticeable vibration above ~90 km/h on newer models (N250 long-term test); clutch/gear-shift roughness in stop-go traffic; sporadic brake-related defects persisting through multiple service visits. | D5: eAuto ('15 Common Pulsar Problems'); MotorBeam N250 long-term final report; Team-BHP Pulsar 135 vibration thread; Quora sentiment thread (lowest-confidence) | E5: Tier 3/4
A6: Dominar (250/400) | B6: 'Big bike feel' and road presence disproportionate to price; confident braking (dual-channel ABS, large front disc); torquey engine; reliability over high mileage reported by long-term owners; value-for-money vs KTM 390 Duke. | C6: Persistent low/mid-RPM vibration is the single most repeated complaint (dealers reportedly offer an informal fix); uncomfortable pillion seat; parking/low-speed handling challenged by weight; component niggles in long-term ownership (rear disc brake noise ~4,500-5,500 km, clutch cable replacement ~7,500 km, rocker-arm ticking); a forum thread flags rust/reliability regret on one ABS unit. | D6: Team-BHP 10,000 km Dominar D400 review; Cartoq vibration piece; Team-BHP 'Rust, Reliability & Regret' thread | E6: Tier 3/4
A7: Platina (100/110) | B7: Mileage is the dominant, near-universal praise point (self-reported figures up to 81-88 kmpl); strong long-term durability claims (one owner cites 150,000 km without breakdown); low running/service costs; good low-speed city maneuverability. | C7: Weak top-end performance — several owners note it struggles past 55-60 km/h and isn't suited to highway use; stability concerns at speed or when larger vehicles pass (safety-relevant); underpowered headlight for night riding; brakes cited as a weak point by several reviewers; occasional mileage-vs-claim gap (one owner: 56 kmpl vs an expected ~85). | D7: BikeWale Platina 100 reviews | E7: Tier 4
A8: Freedom 125 (CNG) | B8: Genuinely competitive running-cost economics (cited as low as ₹1/km); mileage broadly meets or exceeds ARAI in city conditions per BikeWale's own test. | C8: Higher service costs than comparable 100cc petrol bikes (CNG-specific components + periodic cylinder inspection); inconsistent/fluctuating RPM blamed on injector/multi-sensor CNG system; repeated auto-choke engagement at cold start reducing real efficiency; at least one detailed review reports service-center technicians lacking training on CNG-specific issues. Sentiment sample is thin — this is a 2025-era launch, not a mature multi-year track record. | D8: BikeWale owner review ('Don't buy this bike' — single detailed review, anecdotal); BikeWale & ZigWheels mileage test pieces | E8: Tier 3/4

Sheet Service_Network_Accessories
A1: Service Network & Official Accessories
A2: Categories 22-23 · Tier 1 official
A4: Field | B4: Value | C4: Source
A5: Network scale | B5: 700+ dealers, 3,000 authorized service dealers, 100 spare-part distributors, 1,000 priority retailers across India. | C5: bajajauto.com/customer-service/spares
A6: Network branding | B6: No current official page uses 'Bajaj ProBiking' — outlets referred to generically as 'Bajaj authorised (service) dealers'. | C6: bajajauto.com (site-wide)
A7: Service locator | B7: https://www.bajajauto.com/customer-service/locate-a-dealer — search by Sales/Service, state/city, or auto-location. | C7: bajajauto.com/customer-service/locate-a-dealer
A8: Service booking | B8: Not published by Bajaj (official site/manuals checked). bajajauto.com's documented 'Online Booking' flow (onlinebooking-faqs) is for vehicle PURCHASE, not service appointments. A 'Bajaj Care' app exists on app stores but is not referenced from bajajauto.com itself. | C8: bajajauto.com/onlinebooking-faqs
A9: Roadside assistance (Bajaj-badged bikes) | B9: Not published by Bajaj (official site/manuals checked) — no program name found for Bajaj motorcycles. (KTM, a brand distributed by Bajaj, has its own separate 5-yr warranty + RSA program — not applicable to Bajaj-badged bikes.) | C9: bajajauto.com/corporate/media-centre (KTM press release, distinct brand)
A10: Genuine spare parts | B10: Ordered via a 'Bajaj Genuine Parts' app; covers brake shoes, cables, sprockets, filters, spark plugs, shock absorbers, headlamps, lubricants. | C10: bajajauto.com/customer-service/spares/learn-more-about-the-parts
A11: Accessories — Dominar 400 | B11: Factory-fitted 'Touring Accessories' range: engine bash plate, leg guard, hand guards, tall visor, navigation stay, USB charging port, redesigned carrier + passenger backrest, separately-sold saddle stay for panniers. No prices published. | C11: bajajauto.com/blogs/bajaj-dominar-400-touring-accessories
A12: Accessories — Freedom 125 | B12: 2-litre auxiliary petrol reserve tank with handlebar switch (standard/factory feature, not an add-on catalogue item). No price shown. | C12: bajajauto.com/bikes/bajaj-freedom/bajaj-freedom-125-ng04
A13: Accessories — other models | B13: Not published by Bajaj (official site/manuals checked) — no dedicated priced accessories catalogue (top box, panniers, crash guards as standalone SKUs) found for Pulsar/Avenger/Platina/CT on bajajauto.com. | C13: bajajauto.com (site-wide search)

Sheet Regulatory
A1: Regulatory / Environmental
A2: Category 26 · Kept separate since regulations change independently of vehicle specs
A4: Field | B4: Value | C4: Source
A5: Emission standard | B5: BS VI, confirmed explicitly in Pulsar N160 & Dominar 250 owner's manuals ('complies to BS VI standards') and stated on the Pulsar 150/NS125/RS200 pages. Applied as current-lineup baseline for all 20 models (India cannot legally sell non-BS-VI new motorcycles); not one-by-one re-confirmed for every model page. | C5: Owner's manuals (bajajauto.com/customer-service/owners-manual); individual model pages
A6: Fuel type | B6: Petrol (all models) except Freedom 125 NG04, which is bi-fuel CNG + petrol reserve. | C6: bajajauto.com/bikes
A7: Freedom 125 CNG environmental claims | B7: Bajaj press releases cite reductions vs petrol equivalents, but figures VARY by release (e.g. '25% lower CO2 / 73.5% CO reduction / 80% less NMHC' in one release vs '26.7% less CO2 / 85% lower NMHC / 43% less NOx' in another) and are labeled 'as per internal evaluations' — not an independently certified standard figure. Treat as directional marketing claims, not a fixed regulatory number. | C7: bajajauto.com/corporate/media-centre press releases
A8: CNG registration/classification | B8: Not published by Bajaj (official site/manuals checked) — no mention found of registration category or 'green plate' status for the Freedom 125 on bajajauto.com. | C8: bajajauto.com (site-wide search)
A9: EV classification | B9: Not applicable — Bajaj's EV motorcycle-adjacent offering (Chetak) is a scooter sold under a separate brand (chetak.com), outside this ICE-motorcycle workbook. | C9: chetak.com

Sheet Assumptions
A1: TCO / Insurance / Financing Assumptions
A2: Categories 18-19, 21 · EDIT the blue cells — every downstream formula in TCO_Calculator reads from here. Not manufacturer data; generic illustrative planning figures for India, Sept 2026.
A4: Assumption | B4: Value | C4: Note
A5: Petrol price (₹/litre, Delhi-ish) | B5: 103 | C5: Editable — varies by state/city and over time
A6: CNG price (₹/kg, Delhi-ish) | B6: 78 | C6: Editable — varies by state/city and over time
A7: Average annual distance (km) | B7: 8000 | C7: Typical personal-use commuter assumption — raise for high-mileage/delivery use
A8: RTO / road tax (% of ex-showroom, one-time) | B8: 0.1 | C8: Varies significantly by state (7-15%+) and by engine cc slab — generic placeholder
A9: Comprehensive insurance, Year 1 (% of ex-showroom) | B9: 0.035 | C9: Own-damage + statutory 5-yr third-party bundled, illustrative only — not a quote
A10: Insurance renewal, own-damage (% of ex-showroom/yr, from Yr 2) | B10: 0.015 | C10: Illustrative — depreciating IDV reduces this each year in reality
A11: Registration/other one-time charges (₹) | B11: 1500 | C11: Smart-card RC, hypothecation, etc. — illustrative flat figure
A12: Annual service cost — commuter (≤160cc) (₹) | B12: 2200 | C12: ASSUMPTION — not a Bajaj-published figure; consumables + labour, Tier-3-informed estimate
A13: Annual service cost — mid (180-250cc) (₹) | B13: 3200 | C13: ASSUMPTION — not a Bajaj-published figure
A14: Annual service cost — performance (≥350cc) (₹) | B14: 4800 | C14: ASSUMPTION — not a Bajaj-published figure; liquid-cooled/DOHC models cost more to service
A15: Resale value at 3 years (% of ex-showroom) | B15: 0.55 | C15: ASSUMPTION — actual resale varies hugely by city, km, condition, accident history (see Resale notes in TCO sheet)
A16: Resale value at 5 years (% of ex-showroom) | B16: 0.4 | C16: ASSUMPTION — same caveat
... A19: Illustrative loan interest rate (% p.a., flat) | B19: 0.11 | C19: ASSUMPTION — not tied to any one bank; two-wheeler loan rates commonly range ~9-16% p.a.

Sheet TCO_Calculator
A1: Total Cost of Ownership Calculator
A2: Category 20 · Formulas pull price from Variants and rates from Assumptions — edit either sheet and this recalculates. Financing/EMI math lives in the columns to the right.
A4: Model | B4: Ex-showroom Price | C4: Assumed Mileage | D4: Unit | E4: Mileage Basis | F4: Service Tier | G4: On-Road Price (est.) | H4: Annual Fuel Cost | I4: Annual Service Cost | J4: Annual Insurance (Yr2+) | K4: Total Annual Running Cost | L4: 3-Yr TCO (pre-resale) | M4: Resale @3yr | N4: 3-Yr Net TCO | O4: 5-Yr TCO (pre-resale) | P4: Resale @5yr | Q4: 5-Yr Net TCO
A5: Bajaj Freedom 125 NG04 | B5: =Variants!$C$5 -> 117499 | C5: 90 | D5: km/kg | E5: Midpoint of independent CNG tests (BikeWale/ZigWheels: 80-104 km/kg) | F5: commuter | G5: =B5*(1+Assumptions!$B$8+Assumptions!$B$9)+Assumptions!$B$11 -> 134861.36 | H5: =(Assumptions!$B$7/C5)*Assumptions!$B$6 -> 6933.3333 | I5: =Assumptions!$B$12 -> 2200 | J5: =B5*Assumptions!$B$10 -> 1762.485 | K5: =H5+I5+J5 -> 10895.818 | L5: =G5+3*K5 -> 167548.82 | M5: =B5*Assumptions!$B$15 -> 64624.45 | N5: =L5-M5 -> 102924.37 | O5: =G5+5*K5 -> 189340.46 | P5: =B5*Assumptions!$B$16 -> 46999.6 | Q5: =O5-P5 -> 142340.86
A6: Pulsar N125 | B6: =Variants!$C$6 -> 92270 | C6: 45 | D6: km/l | E6: ASSUMPTION — no independent figure found; segment-typical 125cc estimate | F6: commuter | G6: =B6*(1+Assumptions!$B$8+Assumptions!$B$9)+Assumptions!$B$11 -> 106226.45 | H6: =(Assumptions!$B$7/C6)*Assumptions!$B$5 -> 18311.111 | I6: =Assumptions!$B$12 -> 2200 | J6: =B6*Assumptions!$B$10 -> 1384.05 | K6: =H6+I6+J6 -> 21895.161 | L6: =G6+3*K6 -> 171911.93 | M6: =B6*Assumptions!$B$15 -> 50748.5 | N6: =L6-M6 -> 121163.43 | O6: =G6+5*K6 -> 215702.26 | P6: =B6*Assumptions!$B$16 -> 36908 | Q6: =O6-P6 -> 178794.26
A7: Pulsar N160 | B7: =Variants!$C$7 -> 122106 | C7: 47 | D7: km/l | E7: Independent owner-reported (BikeWale) | F7: commuter | G7: =B7*(1+Assumptions!$B$8+Assumptions!$B$9)+Assumptions!$B$11 -> 140090.31 | H7: =(Assumptions!$B$7/C7)*Assumptions!$B$5 -> 17531.915 | I7: =Assumptions!$B$12 -> 2200 | J7: =B7*Assumptions!$B$10 -> 1831.59 | K7: =H7+I7+J7 -> 21563.505 | L7: =G7+3*K7 -> 204780.82 | M7: =B7*Assumptions!$B$15 -> 67158.3 | N7: =L7-M7 -> 137622.52 | O7: =G7+5*K7 -> 247907.83 | P7: =B7*Assumptions!$B$16 -> 48842.4 | Q7: =O7-P7 -> 199065.43
A8: Pulsar N250 | B8: =Variants!$C$8 -> 142202 | C8: 38 | D8: km/l | E8: Midpoint of independent tests (BikeWale/MotorBeam: 30-49 km/l) | F8: mid | G8: =B8*(1+Assumptions!$B$8+Assumptions!$B$9)+Assumptions!$B$11 -> 162899.27 | H8: =(Assumptions!$B$7/C8)*Assumptions!$B$5 -> 21684.211 | I8: =Assumptions!$B$13 -> 3200 | J8: =B8*Assumptions!$B$10 -> 2133.03 | K8: =H8+I8+J8 -> 27017.241 | L8: =G8+3*K8 -> 243950.99 | M8: =B8*Assumptions!$B$15 -> 78211.1 | N8: =L8-M8 -> 165739.89 | O8: =G8+5*K8 -> 297985.47 | P8: =B8*Assumptions!$B$16 -> 56880.8 | Q8: =O8-P8 -> 241104.67
A9: Pulsar NS125 | B9: =Variants!$C$9 -> 99622 | C9: 45 | D9: km/l | E9: ASSUMPTION — source site flagged 'insufficient data' | F9: commuter | G9: =B9*(1+Assumptions!$B$8+Assumptions!$B$9)+Assumptions!$B$11 -> 114570.97 | H9: =(Assumptions!$B$7/C9)*Assumptions!$B$5 -> 18311.111 | I9: =Assumptions!$B$12 -> 2200 | J9: =B9*Assumptions!$B$10 -> 1494.33 | K9: =H9+I9+J9 -> 22005.441 | L9: =G9+3*K9 -> 180587.29 | M9: =B9*Assumptions!$B$15 -> 54792.1 | N9: =L9-M9 -> 125795.19 | O9: =G9+5*K9 -> 224598.18 | P9: =B9*Assumptions!$B$16 -> 39848.8 | Q9: =O9-P9 -> 184749.38
A10: Pulsar NS160 | B10: =Variants!$C$10 -> 126301 | C10: 44 | D10: km/l | E10: Independent owner-reported (BikeWale) | F10: commuter | G10: =B10*(1+Assumptions!$B$8+Assumptions!$B$9)+Assumptions!$B$11 -> 144851.64 | H10: =(Assumptions!$B$7/C10)*Assumptions!$B$5 -> 18727.273 | I10: =Assumptions!$B$12 -> 2200 | J10: =B10*Assumptions!$B$10 -> 1894.515 | K10: =H10+I10+J10 -> 22821.788 | L10: =G10+3*K10 -> 213317 | M10: =B10*Assumptions!$B$15 -> 69465.55 | N10: =L10-M10 -> 143851.45 | O10: =G10+5*K10 -> 258960.57 | P10: =B10*Assumptions!$B$16 -> 50520.4 | Q10: =O10-P10 -> 208440.17
A11: Pulsar NS200 | B11: =Variants!$C$11 -> 138302 | C11: 35 | D11: km/l | E11: ASSUMPTION close to ARAI claim — source site flagged 'insufficient data' | F11: mid | G11: =B11*(1+Assumptions!$B$8+Assumptions!$B$9)+Assumptions!$B$11 -> 158472.77 | H11: =(Assumptions!$B$7/C11)*Assumptions!$B$5 -> 23542.857 | I11: =Assumptions!$B$13 -> 3200 | J11: =B11*Assumptions!$B$10 -> 2074.53 | K11: =H11+I11+J11 -> 28817.387 | L11: =G11+3*K11 -> 244924.93 | M11: =B11*Assumptions!$B$15 -> 76066.1 | N11: =L11-M11 -> 168858.83 | O11: =G11+5*K11 -> 302559.71 | P11: =B11*Assumptions!$B$16 -> 55320.8 | Q11: =O11-P11 -> 247238.91
A12: Pulsar NS400Z | B12: =Variants!$C$12 -> 186015 | C12: 28 | D12: km/l | E12: Independent test (Autocar India: 27.5-29.6 km/l) | F12: mid | G12: =B12*(1+Assumptions!$B$8+Assumptions!$B$9)+Assumptions!$B$11 -> 212627.02 | H12: =(Assumptions!$B$7/C12)*Assumptions!$B$5 -> 29428.571 | I12: =Assumptions!$B$13 -> 3200 | J12: =B12*Assumptions!$B$10 -> 2790.225 | K12: =H12+I12+J12 -> 35418.796 | L12: =G12+3*K12 -> 318883.41 | M12: =B12*Assumptions!$B$15 -> 102308.25 | N12: =L12-M12 -> 216575.16 | O12: =G12+5*K12 -> 389721.01 | P12: =B12*Assumptions!$B$16 -> 74406 | Q12: =O12-P12 -> 315315.01
A13: Pulsar RS200 | B13: =Variants!$C$13 -> 180528 | C13: 36 | D13: km/l | E13: Independent test ride (MotorBeam) | F13: mid | G13: =B13*(1+Assumptions!$B$8+Assumptions!$B$9)+Assumptions!$B$11 -> 206399.28 | H13: =(Assumptions!$B$7/C13)*Assumptions!$B$5 -> 22888.889 | I13: =Assumptions!$B$13 -> 3200 | J13: =B13*Assumptions!$B$10 -> 2707.92 | K13: =H13+I13+J13 -> 28796.809 | L13: =G13+3*K13 -> 292789.71 | M13: =B13*Assumptions!$B$15 -> 99290.4 | N13: =L13-M13 -> 193499.31 | O13: =G13+5*K13 -> 350383.32 | P13: =B13*Assumptions!$B$16 -> 72211.2 | Q13: =O13-P13 -> 278172.12
A14: Pulsar 125 | B14: =Variants!$C$14 -> 104318 | C14: 45 | D14: km/l | E14: Midpoint of independent range (BikeWale: 30-60 km/l) | F14: commuter | G14: =B14*(1+Assumptions!$B$8+Assumptions!$B$9)+Assumptions!$B$11 -> 119900.93 | H14: =(Assumptions!$B$7/C14)*Assumptions!$B$5 -> 18311.111 | I14: =Assumptions!$B$12 -> 2200 | J14: =B14*Assumptions!$B$10 -> 1564.77 | K14: =H14+I14+J14 -> 22075.881 | L14: =G14+3*K14 -> 186128.57 | M14: =B14*Assumptions!$B$15 -> 57374.9 | N14: =L14-M14 -> 128753.67 | O14: =G14+5*K14 -> 230280.34 | P14: =B14*Assumptions!$B$16 -> 41727.2 | Q14: =O14-P14 -> 188553.14
A15: Pulsar 150 | B15: =Variants!$C$15 -> 111197 | C15: 48 | D15: km/l | E15: Midpoint of independent range (BikeWale: 33-65 km/l) | F15: commuter | G15: =B15*(1+Assumptions!$B$8+Assumptions!$B$9)+Assumptions!$B$11 -> 127708.6 | H15: =(Assumptions!$B$7/C15)*Assumptions!$B$5 -> 17166.667 | I15: =Assumptions!$B$12 -> 2200 | J15: =B15*Assumptions!$B$10 -> 1667.955 | K15: =H15+I15+J15 -> 21034.622 | L15: =G15+3*K15 -> 190812.46 | M15: =B15*Assumptions!$B$15 -> 61158.35 | N15: =L15-M15 -> 129654.11 | O15: =G15+5*K15 -> 232881.7 | P15: =B15*Assumptions!$B$16 -> 44478.8 | Q15: =O15-P15 -> 188402.9
A16: Pulsar 180 | B16: =Variants!$C$16 -> 122490 | C16: 42 | D16: km/l | E16: ASSUMPTION — too newly relaunched (2026) for independent data | F16: commuter | G16: =B16*(1+Assumptions!$B$8+Assumptions!$B$9)+Assumptions!$B$11 -> 140526.15 | H16: =(Assumptions!$B$7/C16)*Assumptions!$B$5 -> 19619.048 | I16: =Assumptions!$B$12 -> 2200 | J16: =B16*Assumptions!$B$10 -> 1837.35 | K16: =H16+I16+J16 -> 23656.398 | L16: =G16+3*K16 -> 211495.34 | M16: =B16*Assumptions!$B$15 -> 67369.5 | N16: =L16-M16 -> 144125.84 | O16: =G16+5*K16 -> 258808.14 | P16: =B16*Assumptions!$B$16 -> 48996 | Q16: =O16-P16 -> 209812.14
A17: Pulsar 220F | B17: =Variants!$C$17 -> 135582 | C17: 43 | D17: km/l | E17: Independent owner-reported (BikeWale) | F17: mid | G17: =B17*(1+Assumptions!$B$8+Assumptions!$B$9)+Assumptions!$B$11 -> 155385.57 | H17: =(Assumptions!$B$7/C17)*Assumptions!$B$5 -> 19162.791 | I17: =Assumptions!$B$13 -> 3200 | J17: =B17*Assumptions!$B$10 -> 2033.73 | K17: =H17+I17+J17 -> 24396.521 | L17: =G17+3*K17 -> 228575.13 | M17: =B17*Assumptions!$B$15 -> 74570.1 | N17: =L17-M17 -> 154005.03 | O17: =G17+5*K17 -> 277368.17 | P17: =B17*Assumptions!$B$16 -> 54232.8 | Q17: =O17-P17 -> 223135.37
A18: Dominar 250 | B18: =Variants!$C$18 -> 186835 | C18: 32 | D18: km/l | E18: Independent owner-reported (BikeWale) | F18: mid | G18: =B18*(1+Assumptions!$B$8+Assumptions!$B$9)+Assumptions!$B$11 -> 213557.73 | H18: =(Assumptions!$B$7/C18)*Assumptions!$B$5 -> 25750 | I18: =Assumptions!$B$13 -> 3200 | J18: =B18*Assumptions!$B$10 -> 2802.525 | K18: =H18+I18+J18 -> 31752.525 | L18: =G18+3*K18 -> 308815.3 | M18: =B18*Assumptions!$B$15 -> 102759.25 | N18: =L18-M18 -> 206056.05 | O18: =G18+5*K18 -> 372320.35 | P18: =B18*Assumptions!$B$16 -> 74734 | Q18: =O18-P18 -> 297586.35
A19: Dominar 400 | B19: =Variants!$C$19 -> 208270 | C19: 26 | D19: km/l | E19: Midpoint of independent range (BikeWale/Team-BHP: 22-30 km/l) | F19: mid | G19: =B19*(1+Assumptions!$B$8+Assumptions!$B$9)+Assumptions!$B$11 -> 237886.45 | H19: =(Assumptions!$B$7/C19)*Assumptions!$B$5 -> 31692.308 | I19: =Assumptions!$B$13 -> 3200 | J19: =B19*Assumptions!$B$10 -> 3124.05 | K19: =H19+I19+J19 -> 38016.358 | L19: =G19+3*K19 -> 351935.52 | M19: =B19*Assumptions!$B$15 -> 114548.5 | N19: =L19-M19 -> 237387.02 | O19: =G19+5*K19 -> 427968.24 | P19: =B19*Assumptions!$B$16 -> 83308 | Q19: =O19-P19 -> 344660.24
A20: Avenger 220 Cruise | B20: =Variants!$C$20 -> 133617 | C20: 39 | D20: km/l | E20: Independent owner-average (BikeWale) | F20: mid | G20: =B20*(1+Assumptions!$B$8+Assumptions!$B$9)+Assumptions!$B$11 -> 153155.3 | H20: =(Assumptions!$B$7/C20)*Assumptions!$B$5 -> 21128.205 | I20: =Assumptions!$B$13 -> 3200 | J20: =B20*Assumptions!$B$10 -> 2004.255 | K20: =H20+I20+J20 -> 26332.46 | L20: =G20+3*K20 -> 232152.68 | M20: =B20*Assumptions!$B$15 -> 73489.35 | N20: =L20-M20 -> 158663.33 | O20: =G20+5*K20 -> 284817.6 | P20: =B20*Assumptions!$B$16 -> 53446.8 | Q20: =O20-P20 -> 231370.8
A21: Avenger 220 Street | B21: =Variants!$C$21 -> 133617 | C21: 39 | D21: km/l | E21: ASSUMPTION — no distinct figure found, applied Cruise sibling's value | F21: mid | G21: =B21*(1+Assumptions!$B$8+Assumptions!$B$9)+Assumptions!$B$11 -> 153155.3 | H21: =(Assumptions!$B$7/C21)*Assumptions!$B$5 -> 21128.205 | I21: =Assumptions!$B$13 -> 3200 | J21: =B21*Assumptions!$B$10 -> 2004.255 | K21: =H21+I21+J21 -> 26332.46 | L21: =G21+3*K21 -> 232152.68 | M21: =B21*Assumptions!$B$15 -> 73489.35 | N21: =L21-M21 -> 158663.33 | O21: =G21+5*K21 -> 284817.6 | P21: =B21*Assumptions!$B$16 -> 53446.8 | Q21: =O21-P21 -> 231370.8
A22: Platina 100 | B22: =Variants!$C$22 -> 72942 | C22: 75 | D22: km/l | E22: Midpoint of independent range (BikeWale: 65-88 km/l) | F22: commuter | G22: =B22*(1+Assumptions!$B$8+Assumptions!$B$9)+Assumptions!$B$11 -> 84289.17 | H22: =(Assumptions!$B$7/C22)*Assumptions!$B$5 -> 10986.667 | I22: =Assumptions!$B$12 -> 2200 | J22: =B22*Assumptions!$B$10 -> 1094.13 | K22: =H22+I22+J22 -> 14280.797 | L22: =G22+3*K22 -> 127131.56 | M22: =B22*Assumptions!$B$15 -> 40118.1 | N22: =L22-M22 -> 87013.46 | O22: =G22+5*K22 -> 155693.15 | P22: =B22*Assumptions!$B$16 -> 29176.8 | Q22: =O22-P22 -> 126516.35
A23: Platina 110 Drum | B23: =Variants!$C$23 -> 75797 | C23: 65 | D23: km/l | E23: Independent owner-reported (91Wheels) | F23: commuter | G23: =B23*(1+Assumptions!$B$8+Assumptions!$B$9)+Assumptions!$B$11 -> 87529.595 | H23: =(Assumptions!$B$7/C23)*Assumptions!$B$5 -> 12676.923 | I23: =Assumptions!$B$12 -> 2200 | J23: =B23*Assumptions!$B$10 -> 1136.955 | K23: =H23+I23+J23 -> 16013.878 | L23: =G23+3*K23 -> 135571.23 | M23: =B23*Assumptions!$B$15 -> 41688.35 | N23: =L23-M23 -> 93882.879 | O23: =G23+5*K23 -> 167598.99 | P23: =B23*Assumptions!$B$16 -> 30318.8 | Q23: =O23-P23 -> 137280.19
A24: CT 110X | B24: =Variants!$C$24 -> 74930 | C24: 72 | D24: km/l | E24: Midpoint of ARAI-cited and independent test (70-75 km/l) | F24: commuter | G24: =B24*(1+Assumptions!$B$8+Assumptions!$B$9)+Assumptions!$B$11 -> 86545.55 | H24: =(Assumptions!$B$7/C24)*Assumptions!$B$5 -> 11444.444 | I24: =Assumptions!$B$12 -> 2200 | J24: =B24*Assumptions!$B$10 -> 1123.95 | K24: =H24+I24+J24 -> 14768.394 | L24: =G24+3*K24 -> 130850.73 | M24: =B24*Assumptions!$B$15 -> 41211.5 | N24: =L24-M24 -> 89639.233 | O24: =G24+5*K24 -> 160387.52 | P24: =B24*Assumptions!$B$16 -> 29972 | Q24: =O24-P24 -> 130415.52
A27: Financing illustration (any model — reference cell approach)
A28: Example ex-showroom price | B28: =B5 -> 117499
A29: Down payment | B29: =B28*Assumptions!$B$17 -> 23499.8
A30: Loan amount | B30: =B28-B29 -> 93999.2
A31: Tenure (months) | B31: =Assumptions!$B$18 -> 36
A32: Flat interest rate (p.a.) | B32: =Assumptions!$B$19 -> 0.11
A33: Total interest (flat-rate method) | B33: =B29*Assumptions!$B$19*(B31/12) -> 7754.934
A34: Total repayment (loan + interest) | B34: =B30+B33 -> 101754.13
A35: Approx. EMI | B35: =B34/B31 -> 2826.5037
A37: Note: flat-rate interest is a simplification for illustration; real EMIs use reducing-balance amortisation and will differ from this figure. Replace with your lender's actual quote before presenting to a customer.
A39: Resale / Depreciation caveats (Category 21)
A40: The 55%/40% resale assumptions above are ILLUSTRATIVE PLANNING FIGURES ONLY, not a market quote. Real used-bike resale value varies substantially by city (demand differs across metros vs. tier-2/3 towns), odometer reading, physical/mechanical condition, number of prior owners, accident/flood history, and prevailing used-market demand for that specific model. There is no single universal resale price — always get a current valuation (e.g. via OLX/CarDekho-Bikes/local dealer buy-back quotes) for a real transaction.

Sheet Customer_Decision_Profile
A1: Customer Decision Profile — Intake Template
A2: Category 27 · This is NOT vehicle data — it's the questionnaire schema the advisor should collect from a customer and convert into a Customer Requirement Profile for scoring (see Recommendation_Logic).
A4: Field | B4: Prompt / How to Ask | C4: Type | D4: Example Value
A5: Budget | B5: What's your maximum ex-showroom or on-road budget? | C5: Number (INR) | D5: 150000
A6: Monthly EMI comfort | B6: If financing, what monthly EMI is comfortable? | C6: Number (INR) | D6: 4500
A7: Daily distance | B7: How many km do you ride on a typical day? | C7: Number (km) | D7: 25
A8: Monthly distance | B8: Roughly how many km per month? | C8: Number (km) | D8: 700
A9: City/highway split | B9: What % of your riding is city vs highway? | C9: % split | D9: 70% city / 30% highway
A10: Rider height | B10: Your height (helps with seat height fit) | C10: Number (cm) | D10: 168
A11: Rider experience | B11: New rider, <2 years, or experienced? | C11: Enum | D11: New rider
A12: Pillion frequency | B12: How often do you carry a passenger? | C12: Enum: Never/Occasional/Frequent | D12: Occasional
A13: Typical luggage | B13: Do you carry bags/groceries/tools regularly? | C13: Enum: None/Light/Heavy | D13: Light
A14: Family usage | B14: Will family members also ride/use this bike? | C14: Boolean + notes | D14: Yes — spouse also rides
A15: Commute type | B15: Office commute, errands, business/delivery, leisure? | C15: Enum | D15: Office commute
... A25: Scooter/motorcycle preference | B25: Scooter, motorcycle, or either? | C25: Enum | D25: Motorcycle

Sheet Recommendation_Logic
A1: Recommendation Logic — Framework (implement in code, not as RAG text)
A2: Category 28 · This sheet documents the RULES; the companion narrative document includes runnable pseudocode. The LLM should EXPLAIN results using the KB, not decide scoring weights itself.
A4: Step | B4: Stage | C4: Logic
A5: 1 | B5: Collect profile | C5: Gather the Customer_Decision_Profile fields above into a structured Customer Requirement Profile (CRP).
A6: 2 | B6: Hard filter | C6: Eliminate any Variant where Price > Budget, or where a hard constraint fails (e.g. EV/ICE preference, scooter/motorcycle preference, seat height too tall for rider height, pillion required but variant impractical for pillion).
A7: 3 | B7: Score — weighted sum | C7: For each surviving variant, compute a weighted score: Score = Σ(importance_weight[i] × normalized_attribute_score[i]) across mileage, performance (power-to-weight), comfort (derived), safety (ABS config, brake type), technology (feature count), maintenance-cost (service tier + parts cost), resale (assumption %).
A8: 4 | B8: Use-case suitability boost/penalty | C8: Apply a multiplier per Use-Case Suitability sheet logic (see companion doc) matching the customer's commute type/touring frequency/family usage to each model's documented suitability notes.
A9: 5 | B9: Rank & shortlist | C9: Sort by final score; return top 3-5 variants, not a single answer — per the brief, never lock the customer into one brand/model.
A10: 6 | B10: Cross-brand alternatives | C10: If the top Bajaj results still don't clear a minimum score threshold against the CRP, surface entries from the Competitors sheet as alternatives worth considering, explicitly labeled as non-Bajaj options.
A11: 7 | B11: Explain, don't just assert | C11: The LLM explains WHY each shortlisted variant scored well/poorly using the KB's actual fields — e.g. 'Bike X has dual-channel ABS; Bike Y has single-channel ABS' — never bare superlatives like 'safest'.
A12: 8 | B12: Cite tier | C12: Every claim the explanation makes should be traceable to a Sources_Evidence row so the user can see whether it's an official spec or a third-party test result.

Sheet Sources_Evidence
A1: Sources & Evidence — Master Log
A2: Category 29 · Every major fact in this workbook traces to one of these rows.
A4: Source Name | B4: Source URL | C4: Tier | D4: Source Type | E4: Information Covered | F4: Access Date
A5: Bajaj Auto — Bikes master listing | B5: https://www.bajajauto.com/bikes | C5: 1 | D5: OEM website | E5: All 21 models, canonical ex-showroom Delhi prices | F5: 2026-09-05
A6: Bajaj Auto — individual model pages (x20) | B6: https://www.bajajauto.com/bikes/[family]/[model] | C6: 1 | D6: OEM website | E6: Engine specs, brakes, suspension, colours, features per model | F6: 2026-09-05
A7: Bajaj Auto — About/Corporate | B7: https://www.bajajauto.com/about-us/about-bajaj-group ; /bajaj-auto-subsidiaries | C7: 1 | D7: OEM corporate site | E7: Company structure, brand philosophy, portfolio | F7: 2026-09-05
A8: Bajaj Auto — Contact/Support | B8: https://www.bajajauto.com/customer-service/contact-us | C8: 1 | D8: OEM website | E8: Customer care channels | F8: 2026-09-05
A9: Bajaj Auto — Dealer Locator | B9: https://www.bajajauto.com/customer-service/locate-a-dealer | C9: 1 | D9: OEM website | E9: Service network locator | F9: 2026-09-05
A10: Bajaj Auto — Owner's Manual Hub | B10: https://www.bajajauto.com/customer-service/owners-manual | C10: 1 | D10: OEM PDF manuals | E10: Warranty terms, service intervals, oil grade (Pulsar N160, Dominar 250 confirmed) | F10: 2026-09-05
A11: Bajaj Auto — Spares | B11: https://www.bajajauto.com/customer-service/spares | C11: 1 | D11: OEM website | E11: Service network scale (dealer/service-center counts) | F11: 2026-09-05
A12: Bajaj Auto — Media Centre / Press Releases | B12: https://www.bajajauto.com/corporate/media-centre | C12: 1 | D12: OEM press releases | E12: Freedom 125 CNG environmental claims; KTM warranty program (distinct brand) | F12: 2026-09-05
A13: Chetak (Bajaj EV brand, separate site) | B13: https://www.chetak.com/ | C13: 1 | D13: OEM website (sister brand) | E13: EV portfolio note, service touchpoint claim (EV-specific) | F13: 2026-09-05
A14: BikeWale | B14: https://www.bikewale.com/ | C14: 3 | D14: Auto publication | E14: Independent mileage figures, owner reviews/sentiment, competitor comparisons, spec-sheet dimensions/chassis data | F14: 2026-09-05
A15: 91Wheels | B15: https://www.91wheels.com/ | C15: 3 | D15: Auto spec aggregator | E15: Dimensions, brakes, suspension, tyres, transmission, ARAI mileage — fills gaps bajajauto.com omits (marked [T3] in relevant sheets) | F15: 2026-09-05
... A27: Quora (sentiment thread) | B27: https://www.quora.com/ | C27: 4 | D27: Forum/anecdotal | E27: General Bajaj vibration/build-quality sentiment — lowest confidence in this workbook | F27: 2026-09-05
